{
 "symbol": "000660.KS",
 "price": 1830000.0,
 "previousClose": 1836000.0,
 "change": -6000,
 "changePercent": -0.33,
 "marketTime": "2026-07-22 15:30 KST",
 "fetchedAt": "2026-07-22 21:48 KST",
 "days": [
  {
   "date": "2026-07-21",
   "open": 1775000.0,
   "high": 1889000.0,
   "low": 1732000.0,
   "close": 1836000.0,
   "volume": 4639208
  },
  {
   "date": "2026-07-22",
   "open": 1977000.0,
   "high": 2006000.0,
   "low": 1830000.0,
   "close": 1830000.0,
   "volume": 4802637
  }
 ],
 "indicators": {
  "macd": {
   "macd": -125434,
   "signal": -57129,
   "hist": -68305,
   "read": "하락 모멘텀 (MACD < 시그널)"
  },
  "atr": {
   "value": 224615,
   "pct": 12.3,
   "read": "일 평균 변동폭 12.3% — 변동성 매우 큼"
  },
  "adx": {
   "adx": 28.4,
   "pdi": 20.2,
   "ndi": 34.6,
   "read": "추세 강함 · -DI 우위(하락)"
  },
  "kdj": {
   "k": 23.0,
   "d": 22.9,
   "j": 23.3,
   "read": "중립 구간 · K > D (단기 상승 우위)"
  },
  "volume": {
   "today": 4802637,
   "ma20": 6469055,
   "ratio": 0.74,
   "read": "20일 평균 대비 0.7배 — 평균 수준"
  }
 }
}